asyncmrcache/internals.cpython-35m-x86_64-linux-gnu.so
asyncmrcache/__init__.py
asyncmrcache/client.py
asyncmrcache-0.2.dist-info/zip-safe
asyncmrcache-0.2.dist-info/top_level.txt
asyncmrcache-0.2.dist-info/RECORD
asyncmrcache-0.2.dist-info/METADATA
asyncmrcache-0.2.dist-info/LICENSE
asyncmrcache-0.2.dist-info/WHEEL
