Metadata-Version: 2.1
Name: asyncmrcache
Version: 0.2
Summary: Python asyncio mrmrcache client
Home-page: https://github.com/MarkReedZ/asyncmrcache
Author: Mark Reed
Author-email: mark@untilfluent.com
License: MIT License
Platform: UNKNOWN
Classifier: Intended Audience :: Developers
Classifier: Programming Language :: Python
Classifier: Programming Language :: Python :: 3
Classifier: Programming Language :: Python :: 3.5
Classifier: Programming Language :: Python :: 3.6
